fabrica_de_bere/__init__.py
fabrica_de_bere/beer.py
fabrica_de_bere/cache.py
fabrica_de_bere/config.py
fabrica_de_bere/fabrica_de_bere.py
fabrica_de_bere-0.0.3.dist-info/METADATA
fabrica_de_bere-0.0.3.dist-info/WHEEL
fabrica_de_bere-0.0.3.dist-info/top_level.txt
fabrica_de_bere-0.0.3.dist-info/RECORD
