Metadata-Version: 2.1
Name: fabrica-de-bere
Version: 0.0.3
Summary: A small example package
Author-email: Example Author <author@example.com>
Project-URL: Homepage, https://github.com/pypa/sampleproject
Project-URL: Bug Tracker, https://github.com/pypa/sampleproject/issues
Classifier: Programming Language :: Python :: 3
Classifier: License :: OSI Approved :: MIT License
Classifier: Operating System :: OS Independent
Requires-Python: >=3.7
Requires-Dist: requests (==2.28.1)
Requires-Dist: httpretty
Requires-Dist: pytest-lazy-fixture
